reporter/__init__.py
reporter/decorators.py
reporter/utils.py
logging_reporter-1.0.0.dist-info/LICENSE
logging_reporter-1.0.0.dist-info/METADATA
logging_reporter-1.0.0.dist-info/WHEEL
logging_reporter-1.0.0.dist-info/top_level.txt
logging_reporter-1.0.0.dist-info/RECORD
