Metadata-Version: 2.1
Name: logging-reporter
Version: 1.0.0
Summary: Lightweight logger decorators for python
Home-page: https://github.com/2019342a/reporter
Author: Theofilos Alexiou
Author-email: theofilosalexiou@gmail.com
License: MIT
Platform: UNKNOWN
Classifier: Operating System :: OS Independent
Classifier: Intended Audience :: Developers
Classifier: License :: OSI Approved :: MIT License
Classifier: Programming Language :: Python :: 3
Classifier: Programming Language :: Python :: 3 :: Only
Requires-Dist: colorlog (==4.2.1)
